{"expires_at": 1766787067.309139, "value": {"player": "Adem Bona", "source": "nba_stats", "fetched_at": 1766783463.278162, "season": null, "logs": [{"SEASON_ID": "22025", "Player_ID": 1641737, "Game_ID": "0022500410", "date": "2025-12-23 00:00:00", "matchup": "PHI vs. BKN", "result": "L", "minutes": 19, "fgm": 2, "fga": 2, "FG_PCT": 1.0, "fg3m": 0, "fg3a": 0, "FG3_PCT": 0.0, "ftm": 0, "fta": 0, "FT_PCT": 0.0, "OREB": 0, "DREB": 1, "rebounds": 1, "assists": 0, "steals": 0, "blocks": 0, "turnovers": 0, "PF": 5, "points": 4, "plus_minus": 6, "VIDEO_AVAILABLE": 1, "pra": 5, "pts_reb": 5, "pts_ast": 4, "reb_ast": 1, "fantasy": 5.2, "home": true, "opponent": "BKN", "player": "Adem Bona"}, {"SEASON_ID": "22025", "Player_ID": 1641737, "Game_ID": "0022500387", "date": "2025-12-20 00:00:00", "matchup": "PHI vs. DAL", "result": "W", "minutes": 25, "fgm": 2, "fga": 6, "FG_PCT": 0.333, "fg3m": 1, "fg3a": 1, "FG3_PCT": 1.0, "ftm": 5, "fta": 6, "FT_PCT": 0.833, "OREB": 6, "DREB": 2, "rebounds": 8, "assists": 0, "steals": 1, "blocks": 1, "turnovers": 1, "PF": 2, "points": 10, "plus_minus": 17, "VIDEO_AVAILABLE": 1, "pra": 18, "pts_reb": 18, "pts_ast": 10, "reb_ast": 8, "fantasy": 24.6, "home": true, "opponent": "DAL", "player": "Adem Bona"}, {"SEASON_ID": "22025", "Player_ID": 1641737, "Game_ID": "0022500382", "date": "2025-12-19 00:00:00", "matchup": "PHI @ NYK", "result": "W", "minutes": 15, "fgm": 1, "fga": 1, "FG_PCT": 1.0, "fg3m": 0, "fg3a": 0, "FG3_PCT": 0.0, "ftm": 1, "fta": 2, "FT_PCT": 0.5, "OREB": 2, "DREB": 0, "rebounds": 2, "assists": 0, "steals": 0, "blocks": 3, "turnovers": 1, "PF": 4, "points": 3, "plus_minus": -1, "VIDEO_AVAILABLE": 1, "pra": 5, "pts_reb": 5, "pts_ast": 3, "reb_ast": 2, "fantasy": 13.4, "home": false, "opponent": "NYK", "player": "Adem Bona"}, {"SEASON_ID": "22025", "Player_ID": 1641737, "Game_ID": "0022500348", "date": "2025-12-05 00:00:00", "matchup": "PHI @ MIL", "result": "W", "minutes": 24, "fgm": 4, "fga": 7, "FG_PCT": 0.571, "fg3m": 0, "fg3a": 0, "FG3_PCT": 0.0, "ftm": 2, "fta": 2, "FT_PCT": 1.0, "OREB": 3, "DREB": 3, "rebounds": 6, "assists": 0, "steals": 1, "blocks": 0, "turnovers": 1, "PF": 4, "points": 10, "plus_minus": 9, "VIDEO_AVAILABLE": 1, "pra": 16, "pts_reb": 16, "pts_ast": 10, "reb_ast": 6, "fantasy": 19.2, "home": false, "opponent": "MIL", "player": "Adem Bona"}, {"SEASON_ID": "22025", "Player_ID": 1641737, "Game_ID": "0022500333", "date": "2025-12-04 00:00:00", "matchup": "PHI vs. GSW", "result": "W", "minutes": 6, "fgm": 1, "fga": 2, "FG_PCT": 0.5, "fg3m": 0, "fg3a": 0, "FG3_PCT": 0.0, "ftm": 0, "fta": 2, "FT_PCT": 0.0, "OREB": 2, "DREB": 0, "rebounds": 2, "assists": 0, "steals": 0, "blocks": 0, "turnovers": 0, "PF": 0, "points": 2, "plus_minus": -2, "VIDEO_AVAILABLE": 1, "pra": 4, "pts_reb": 4, "pts_ast": 2, "reb_ast": 2, "fantasy": 4.4, "home": true, "opponent": "GSW", "player": "Adem Bona"}, {"SEASON_ID": "22025", "Player_ID": 1641737, "Game_ID": "0022500318", "date": "2025-12-02 00:00:00", "matchup": "PHI vs. WAS", "result": "W", "minutes": 22, "fgm": 1, "fga": 1, "FG_PCT": 1.0, "fg3m": 0, "fg3a": 0, "FG3_PCT": 0.0, "ftm": 2, "fta": 2, "FT_PCT": 1.0, "OREB": 2, "DREB": 3, "rebounds": 5, "assists": 0, "steals": 0, "blocks": 1, "turnovers": 0, "PF": 4, "points": 4, "plus_minus": 26, "VIDEO_AVAILABLE": 1, "pra": 9, "pts_reb": 9, "pts_ast": 4, "reb_ast": 5, "fantasy": 13.0, "home": true, "opponent": "WAS", "player": "Adem Bona"}, {"SEASON_ID": "22025", "Player_ID": 1641737, "Game_ID": "0022500304", "date": "2025-11-30 00:00:00", "matchup": "PHI vs. ATL", "result": "L", "minutes": 22, "fgm": 1, "fga": 3, "FG_PCT": 0.333, "fg3m": 0, "fg3a": 1, "FG3_PCT": 0.0, "ftm": 2, "fta": 2, "FT_PCT": 1.0, "OREB": 2, "DREB": 1, "rebounds": 3, "assists": 0, "steals": 0, "blocks": 2, "turnovers": 2, "PF": 3, "points": 4, "plus_minus": 2, "VIDEO_AVAILABLE": 1, "pra": 7, "pts_reb": 7, "pts_ast": 4, "reb_ast": 3, "fantasy": 11.6, "home": true, "opponent": "ATL", "player": "Adem Bona"}, {"SEASON_ID": "22025", "Player_ID": 1641737, "Game_ID": "0022500070", "date": "2025-11-28 00:00:00", "matchup": "PHI @ BKN", "result": "W", "minutes": 23, "fgm": 6, "fga": 7, "FG_PCT": 0.857, "fg3m": 1, "fg3a": 1, "FG3_PCT": 1.0, "ftm": 0, "fta": 0, "FT_PCT": 0.0, "OREB": 2, "DREB": 4, "rebounds": 6, "assists": 0, "steals": 0, "blocks": 3, "turnovers": 2, "PF": 4, "points": 13, "plus_minus": 6, "VIDEO_AVAILABLE": 1, "pra": 19, "pts_reb": 19, "pts_ast": 13, "reb_ast": 6, "fantasy": 27.2, "home": false, "opponent": "BKN", "player": "Adem Bona"}, {"SEASON_ID": "22025", "Player_ID": 1641737, "Game_ID": "0022500041", "date": "2025-11-14 00:00:00", "matchup": "PHI @ DET", "result": "L", "minutes": 9, "fgm": 1, "fga": 2, "FG_PCT": 0.5, "fg3m": 0, "fg3a": 0, "FG3_PCT": 0.0, "ftm": 0, "fta": 0, "FT_PCT": 0.0, "OREB": 2, "DREB": 3, "rebounds": 5, "assists": 0, "steals": 0, "blocks": 1, "turnovers": 0, "PF": 2, "points": 2, "plus_minus": -9, "VIDEO_AVAILABLE": 1, "pra": 7, "pts_reb": 7, "pts_ast": 2, "reb_ast": 5, "fantasy": 11.0, "home": false, "opponent": "DET", "player": "Adem Bona"}, {"SEASON_ID": "22025", "Player_ID": 1641737, "Game_ID": "0022500209", "date": "2025-11-11 00:00:00", "matchup": "PHI vs. BOS", "result": "W", "minutes": 15, "fgm": 1, "fga": 1, "FG_PCT": 1.0, "fg3m": 0, "fg3a": 0, "FG3_PCT": 0.0, "ftm": 0, "fta": 2, "FT_PCT": 0.0, "OREB": 0, "DREB": 4, "rebounds": 4, "assists": 0, "steals": 0, "blocks": 2, "turnovers": 0, "PF": 0, "points": 2, "plus_minus": -8, "VIDEO_AVAILABLE": 1, "pra": 6, "pts_reb": 6, "pts_ast": 2, "reb_ast": 4, "fantasy": 12.8, "home": true, "opponent": "BOS", "player": "Adem Bona"}, {"SEASON_ID": "22025", "Player_ID": 1641737, "Game_ID": "0022500195", "date": "2025-11-09 00:00:00", "matchup": "PHI vs. DET", "result": "L", "minutes": 12, "fgm": 0, "fga": 1, "FG_PCT": 0.0, "fg3m": 0, "fg3a": 0, "FG3_PCT": 0.0, "ftm": 2, "fta": 2, "FT_PCT": 1.0, "OREB": 1, "DREB": 3, "rebounds": 4, "assists": 0, "steals": 1, "blocks": 3, "turnovers": 0, "PF": 1, "points": 2, "plus_minus": 8, "VIDEO_AVAILABLE": 1, "pra": 6, "pts_reb": 6, "pts_ast": 2, "reb_ast": 4, "fantasy": 18.8, "home": true, "opponent": "DET", "player": "Adem Bona"}, {"SEASON_ID": "22025", "Player_ID": 1641737, "Game_ID": "0022500184", "date": "2025-11-08 00:00:00", "matchup": "PHI vs. TOR", "result": "W", "minutes": 6, "fgm": 0, "fga": 0, "FG_PCT": 0.0, "fg3m": 0, "fg3a": 0, "FG3_PCT": 0.0, "ftm": 0, "fta": 0, "FT_PCT": 0.0, "OREB": 0, "DREB": 2, "rebounds": 2, "assists": 0, "steals": 0, "blocks": 1, "turnovers": 0, "PF": 1, "points": 0, "plus_minus": -13, "VIDEO_AVAILABLE": 1, "pra": 2, "pts_reb": 2, "pts_ast": 0, "reb_ast": 2, "fantasy": 5.4, "home": true, "opponent": "TOR", "player": "Adem Bona"}, {"SEASON_ID": "22025", "Player_ID": 1641737, "Game_ID": "0022500171", "date": "2025-11-05 00:00:00", "matchup": "PHI @ CLE", "result": "L", "minutes": 18, "fgm": 1, "fga": 3, "FG_PCT": 0.333, "fg3m": 0, "fg3a": 1, "FG3_PCT": 0.0, "ftm": 2, "fta": 5, "FT_PCT": 0.4, "OREB": 2, "DREB": 2, "rebounds": 4, "assists": 0, "steals": 2, "blocks": 0, "turnovers": 3, "PF": 2, "points": 4, "plus_minus": -16, "VIDEO_AVAILABLE": 1, "pra": 8, "pts_reb": 8, "pts_ast": 4, "reb_ast": 4, "fantasy": 11.8, "home": false, "opponent": "CLE", "player": "Adem Bona"}, {"SEASON_ID": "22025", "Player_ID": 1641737, "Game_ID": "0022500167", "date": "2025-11-04 00:00:00", "matchup": "PHI @ CHI", "result": "L", "minutes": 22, "fgm": 1, "fga": 2, "FG_PCT": 0.5, "fg3m": 0, "fg3a": 0, "FG3_PCT": 0.0, "ftm": 0, "fta": 0, "FT_PCT": 0.0, "OREB": 2, "DREB": 2, "rebounds": 4, "assists": 0, "steals": 0, "blocks": 1, "turnovers": 0, "PF": 1, "points": 2, "plus_minus": -3, "VIDEO_AVAILABLE": 1, "pra": 6, "pts_reb": 6, "pts_ast": 2, "reb_ast": 4, "fantasy": 9.8, "home": false, "opponent": "CHI", "player": "Adem Bona"}, {"SEASON_ID": "22025", "Player_ID": 1641737, "Game_ID": "0022500149", "date": "2025-11-02 00:00:00", "matchup": "PHI @ BKN", "result": "W", "minutes": 14, "fgm": 1, "fga": 2, "FG_PCT": 0.5, "fg3m": 0, "fg3a": 0, "FG3_PCT": 0.0, "ftm": 0, "fta": 0, "FT_PCT": 0.0, "OREB": 1, "DREB": 2, "rebounds": 3, "assists": 0, "steals": 1, "blocks": 1, "turnovers": 0, "PF": 4, "points": 2, "plus_minus": -4, "VIDEO_AVAILABLE": 1, "pra": 5, "pts_reb": 5, "pts_ast": 2, "reb_ast": 3, "fantasy": 11.6, "home": false, "opponent": "BKN", "player": "Adem Bona"}, {"SEASON_ID": "22025", "Player_ID": 1641737, "Game_ID": "0022500021", "date": "2025-10-31 00:00:00", "matchup": "PHI vs. BOS", "result": "L", "minutes": 11, "fgm": 1, "fga": 2, "FG_PCT": 0.5, "fg3m": 0, "fg3a": 0, "FG3_PCT": 0.0, "ftm": 0, "fta": 0, "FT_PCT": 0.0, "OREB": 1, "DREB": 2, "rebounds": 3, "assists": 0, "steals": 0, "blocks": 2, "turnovers": 1, "PF": 1, "points": 2, "plus_minus": -10, "VIDEO_AVAILABLE": 1, "pra": 5, "pts_reb": 5, "pts_ast": 2, "reb_ast": 3, "fantasy": 10.6, "home": true, "opponent": "BOS", "player": "Adem Bona"}, {"SEASON_ID": "22025", "Player_ID": 1641737, "Game_ID": "0022500123", "date": "2025-10-28 00:00:00", "matchup": "PHI @ WAS", "result": "W", "minutes": 18, "fgm": 1, "fga": 3, "FG_PCT": 0.333, "fg3m": 0, "fg3a": 0, "FG3_PCT": 0.0, "ftm": 0, "fta": 0, "FT_PCT": 0.0, "OREB": 3, "DREB": 2, "rebounds": 5, "assists": 0, "steals": 0, "blocks": 5, "turnovers": 1, "PF": 0, "points": 2, "plus_minus": 5, "VIDEO_AVAILABLE": 1, "pra": 7, "pts_reb": 7, "pts_ast": 2, "reb_ast": 5, "fantasy": 22.0, "home": false, "opponent": "WAS", "player": "Adem Bona"}, {"SEASON_ID": "22025", "Player_ID": 1641737, "Game_ID": "0022500114", "date": "2025-10-27 00:00:00", "matchup": "PHI vs. ORL", "result": "W", "minutes": 25, "fgm": 2, "fga": 3, "FG_PCT": 0.667, "fg3m": 0, "fg3a": 0, "FG3_PCT": 0.0, "ftm": 3, "fta": 5, "FT_PCT": 0.6, "OREB": 2, "DREB": 2, "rebounds": 4, "assists": 1, "steals": 0, "blocks": 3, "turnovers": 0, "PF": 2, "points": 7, "plus_minus": 21, "VIDEO_AVAILABLE": 1, "pra": 12, "pts_reb": 11, "pts_ast": 8, "reb_ast": 5, "fantasy": 22.3, "home": true, "opponent": "ORL", "player": "Adem Bona"}, {"SEASON_ID": "22025", "Player_ID": 1641737, "Game_ID": "0022500102", "date": "2025-10-25 00:00:00", "matchup": "PHI vs. CHA", "result": "W", "minutes": 12, "fgm": 0, "fga": 1, "FG_PCT": 0.0, "fg3m": 0, "fg3a": 0, "FG3_PCT": 0.0, "ftm": 1, "fta": 2, "FT_PCT": 0.5, "OREB": 0, "DREB": 0, "rebounds": 0, "assists": 1, "steals": 1, "blocks": 1, "turnovers": 0, "PF": 1, "points": 1, "plus_minus": -6, "VIDEO_AVAILABLE": 1, "pra": 2, "pts_reb": 1, "pts_ast": 2, "reb_ast": 1, "fantasy": 8.5, "home": true, "opponent": "CHA", "player": "Adem Bona"}, {"SEASON_ID": "22025", "Player_ID": 1641737, "Game_ID": "0022500083", "date": "2025-10-22 00:00:00", "matchup": "PHI @ BOS", "result": "W", "minutes": 15, "fgm": 0, "fga": 0, "FG_PCT": 0.0, "fg3m": 0, "fg3a": 0, "FG3_PCT": 0.0, "ftm": 0, "fta": 0, "FT_PCT": 0.0, "OREB": 1, "DREB": 2, "rebounds": 3, "assists": 1, "steals": 0, "blocks": 0, "turnovers": 2, "PF": 3, "points": 0, "plus_minus": 4, "VIDEO_AVAILABLE": 1, "pra": 4, "pts_reb": 3, "pts_ast": 1, "reb_ast": 4, "fantasy": 3.0999999999999996, "home": false, "opponent": "BOS", "player": "Adem Bona"}]}}